odoo/addons/sale_brand/README.rst
odoo/addons/sale_brand/__init__.py
odoo/addons/sale_brand/__manifest__.py
odoo/addons/sale_brand/i18n/es_AR.po
odoo/addons/sale_brand/i18n/fr_FR.po
odoo/addons/sale_brand/i18n/hr.po
odoo/addons/sale_brand/i18n/it.po
odoo/addons/sale_brand/i18n/nl.po
odoo/addons/sale_brand/i18n/sale_brand.pot
odoo/addons/sale_brand/i18n/zh_CN.po
odoo/addons/sale_brand/models/__init__.py
odoo/addons/sale_brand/models/crm_team.py
odoo/addons/sale_brand/models/sale_order.py
odoo/addons/sale_brand/readme/CONTRIBUTORS.rst
odoo/addons/sale_brand/readme/CREDITS.rst
odoo/addons/sale_brand/readme/DESCRIPTION.rst
odoo/addons/sale_brand/readme/USAGE.rst
odoo/addons/sale_brand/static/description/icon.png
odoo/addons/sale_brand/static/description/index.html
odoo/addons/sale_brand/tests/__init__.py
odoo/addons/sale_brand/tests/test_sale_order.py
odoo/addons/sale_brand/views/crm_team_views.xml
odoo/addons/sale_brand/views/sale_views.xml
odoo/addons/sale_brand/wizard/__init__.py
odoo/addons/sale_brand/wizard/sale_make_invoice_advance.py
odoo14_addon_sale_brand-14.0.1.0.2.dist-info/METADATA
odoo14_addon_sale_brand-14.0.1.0.2.dist-info/WHEEL
odoo14_addon_sale_brand-14.0.1.0.2.dist-info/top_level.txt
odoo14_addon_sale_brand-14.0.1.0.2.dist-info/RECORD
