Metadata-Version: 2.1
Name: odoo14-addon-sale-brand
Version: 14.0.1.0.2
Summary: Send branded sales orders
Home-page: https://github.com/OCA/brand
Author: Open Source Integrators, Odoo Community Association (OCA)
Author-email: support@odoo-community.org
License: AGPL-3
Platform: UNKNOWN
Classifier: Programming Language :: Python
Classifier: Framework :: Odoo
Classifier: Framework :: Odoo :: 14.0
Classifier: License :: OSI Approved :: GNU Affero General Public License v3
Classifier: Development Status :: 4 - Beta
Requires-Python: >=3.6
Requires-Dist: odoo14-addon-account-brand
Requires-Dist: odoo14-addon-analytic-brand
Requires-Dist: odoo14-addon-brand
Requires-Dist: odoo <14.1dev,>=14.0a
